enyal/__init__.py
enyal/__main__.py
enyal/py.typed
enyal/cli/__init__.py
enyal/cli/main.py
enyal/core/__init__.py
enyal/core/retrieval.py
enyal/core/ssl_config.py
enyal/core/store.py
enyal/embeddings/__init__.py
enyal/embeddings/engine.py
enyal/mcp/__init__.py
enyal/mcp/__main__.py
enyal/mcp/server.py
enyal/models/__init__.py
enyal/models/context.py
enyal-0.2.0.dist-info/METADATA
enyal-0.2.0.dist-info/WHEEL
enyal-0.2.0.dist-info/entry_points.txt
enyal-0.2.0.dist-info/licenses/LICENSE
enyal-0.2.0.dist-info/RECORD
