Metadata-Version: 2.4
Name: enyal
Version: 0.2.0
Summary: Persistent, queryable memory for AI coding agents
Project-URL: Homepage, https://github.com/seancorkum/enyal
Project-URL: Documentation, https://github.com/seancorkum/enyal#readme
Project-URL: Repository, https://github.com/seancorkum/enyal
Project-URL: Issues, https://github.com/seancorkum/enyal/issues
Author: Sean Corkum
License: MIT
License-File: LICENSE
Keywords: agents,ai,context,llm,mcp,memory
Classifier: Development Status :: 3 - Alpha
Classifier: Intended Audience :: Developers
Classifier: License :: OSI Approved :: MIT License
Classifier: Operating System :: MacOS :: MacOS X
Classifier: Operating System :: Microsoft :: Windows
Classifier: Operating System :: POSIX :: Linux
Classifier: Programming Language :: Python :: 3
Classifier: Programming Language :: Python :: 3.11
Classifier: Programming Language :: Python :: 3.12
Classifier: Programming Language :: Python :: 3.13
Classifier: Topic :: Scientific/Engineering :: Artificial Intelligence
Classifier: Topic :: Software Development :: Libraries :: Python Modules
Requires-Python: >=3.11
Requires-Dist: fastmcp>=2.0.0
Requires-Dist: numpy<2.0.0,>=1.26.0; python_version < '3.13'
Requires-Dist: numpy>=2.0.0; python_version >= '3.13'
Requires-Dist: pydantic>=2.0.0
Requires-Dist: sentence-transformers>=3.0.0
Requires-Dist: sqlite-vec>=0.1.0
Provides-Extra: dev
Requires-Dist: mypy>=1.10.0; extra == 'dev'
Requires-Dist: pytest-asyncio>=0.23.0; extra == 'dev'
Requires-Dist: pytest-cov>=4.0.0; extra == 'dev'
Requires-Dist: pytest>=8.0.0; extra == 'dev'
Requires-Dist: ruff>=0.4.0; extra == 'dev'
Requires-Dist: types-requests>=2.31.0; extra == 'dev'
Provides-Extra: onnx
Requires-Dist: onnxruntime>=1.18.0; extra == 'onnx'
Requires-Dist: optimum>=1.19.0; extra == 'onnx'
